daeda/__init__.py
daeda-0.0.1.dist-info/LICENSE
daeda-0.0.1.dist-info/METADATA
daeda-0.0.1.dist-info/WHEEL
daeda-0.0.1.dist-info/top_level.txt
daeda-0.0.1.dist-info/RECORD
