Metadata-Version: 2.1
Name: daeda
Version: 0.0.1
Summary: A scalable view-based data analysis library
Home-page: UNKNOWN
Author: nbreitkopf
License: UNKNOWN
Platform: UNKNOWN
Classifier: Programming Language :: Python :: 3
Classifier: License :: OSI Approved :: MIT License
Classifier: Operating System :: OS Independent
Requires-Python: >=3.6
